worker/__init__.py
worker/constants.py
worker/exceptions.py
worker/app/__init__.py
worker/app/modules/__init__.py
worker/app/modules/activity_module.py
worker/app/modules/connection_module.py
worker/app/modules/depth_activity_module.py
worker/app/modules/scheduler.py
worker/app/modules/time_activity_module.py
worker/app/modules/trigger.py
worker/data/__init__.py
worker/data/alert.py
worker/data/api.py
worker/data/enums.py
worker/data/json_encoder.py
worker/data/math.py
worker/data/operations.py
worker/data/serialization.py
worker/data/task_handler.py
worker/data/two_way_dict.py
worker/data/unit_conversions.py
worker/data/wits.py
worker/data/activity/__init__.py
worker/data/activity/activity_grouping.py
worker/event/__init__.py
worker/event/event_handler.py
worker/event/scheduled.py
worker/event/stream.py
worker/mixins/__init__.py
worker/mixins/logging.py
worker/mixins/rollbar.py
worker/partial_rerun_merge/__init__.py
worker/partial_rerun_merge/merge.py
worker/partial_rerun_merge/models.py
worker/partial_rerun_merge/progress.py
worker/state/__init__.py
worker/state/mixins.py
worker/state/state.py
worker/test/__init__.py
worker/test/lambda_function_test_run.py
worker/test/utils.py
worker/test/local_testing/__init__.py
worker/test/local_testing/to_local_transfer.py
worker/wellbore/__init__.py
worker/wellbore/factory.py
worker/wellbore/measured_depth_finder.py
worker/wellbore/sections_mixin.py
worker/wellbore/wellbore.py
worker/wellbore/model/__init__.py
worker/wellbore/model/ann.py
worker/wellbore/model/annulus.py
worker/wellbore/model/drillstring.py
worker/wellbore/model/drillstring_components.py
worker/wellbore/model/element.py
worker/wellbore/model/enums.py
worker/wellbore/model/hole.py
worker/wellbore/model/hole_section.py
worker/wellbore/model/riser.py
corva_worker_python-2.2.2.dist-info/METADATA
corva_worker_python-2.2.2.dist-info/WHEEL
corva_worker_python-2.2.2.dist-info/top_level.txt
corva_worker_python-2.2.2.dist-info/RECORD
