Metadata-Version: 2.4
Name: corva-worker-python
Version: 2.2.2
Summary: SDK for interacting with Corva
Home-page: https://github.com/corva-ai/corva-worker-python
Author: Jordan Ambra <jordan.ambra@corva.ai>, Mohammadreza Kamyab <m.kamyab@corva.ai>
License: Unlicensed
Keywords: corva,worker
Classifier: Development Status :: 5 - Production/Stable
Classifier: Intended Audience :: Developers
Classifier: Operating System :: OS Independent
Classifier: Programming Language :: Python
Classifier: Programming Language :: Python :: 3
Classifier: Programming Language :: Python :: 3.13
Classifier: Programming Language :: Python :: 3.14
Classifier: Topic :: Software Development :: Libraries
Requires-Python: >=3.13
Requires-Dist: numpy>=2.3.5
Requires-Dist: redis>=5.2.1
Requires-Dist: requests>=2.32.5
Requires-Dist: simplejson>=3.20.2
Requires-Dist: urllib3>=2.5.0
Dynamic: author
Dynamic: classifier
Dynamic: home-page
Dynamic: keywords
Dynamic: license
Dynamic: requires-dist
Dynamic: requires-python
Dynamic: summary
